msgraph/__init__.py
msgraph/api.py
msgraph/base.py
msgraph/calendar.py
msgraph/exception.py
msgraph/files.py
msgraph/group.py
msgraph/sites.py
msgraph/user.py
python_msgraph-0.2.8.dist-info/METADATA
python_msgraph-0.2.8.dist-info/NOTICE
python_msgraph-0.2.8.dist-info/WHEEL
python_msgraph-0.2.8.dist-info/top_level.txt
python_msgraph-0.2.8.dist-info/RECORD
