Metadata-Version: 2.1
Name: python-msgraph
Version: 0.2.8
Summary: Python wrapper to the Microsoft Graph API
Home-page: https://github.com/WMInfoTech/python-msgraph
Author: Doug Fenstermacher
Author-email: dpfens@wm.edu
License: Apache2
Project-URL: Source, https://github.com/WMInfoTech/python-msgraph
Project-URL: Tracker, https://github.com/WMInfoTech/python-msgraph/issues
Keywords: microsoft,graph,api,group,calendar,event,site,list,listitem,drive,file
Platform: UNKNOWN
